{"URL": "https://www.wired.com/1999/12/spin-doctors", "heading": "spin doctors", "subheading": "dvd the vast storage capacity of digital videodisc has given the creators of the dvd monthly circuit free rein to overproduce the traditional music fanzine. viewers must slog through unreadable menus with inscrutable names, then endure long interstitial introductions before finally getting down to the rock. the meat of the thing \u2013 cool alterna-bands like [\u2026]", "author": "bob parks", "category": "not found", "type": "article", "timestamp": "12.01.1999 12:00 PM", "text": "dvdthe vast storage capacity of digital videodisc has given the creators of the dvd monthly circuit free rein to overproduce the traditional music fanzine. viewers must slog through unreadable menus with inscrutable names, then endure long interstitial introductions before finally getting down to the rock.the meat of the thing - cool alterna-bands like cake, wilco, roots, dj spooky, guided by voices, and grant lee buffalo - is also hampered by unchecked creativity. each interview is amped up with some annoying conceit: in one section, the cardigans go bowling and the alley manager acts as interlocutor; elsewhere, a very generous beck must converse with a stupid synthesized voice.this attention to padding gigabytes is the same impulse that killed the first generation of cd-rom magazines, such as medio magazine (belly-up in april 1995) and blender (r.i.p., june 1997). but venues to watch good music are scarce in the age of the all-sitcom mtv, and circuit sure can show videos. if its creators would stop trying to muck up the title's otherwise solid content, i won't ever look at magazines the same.circuit: $14.95. quickband network:(888) 383 6247, www.quickband.com.street credrest in inner peacerip-and-roll highwaybiodetectivemagic markershead triphelping handelectric avenuereadmemusicpocket portalwords for windowsthe boy mechanicspin doctorsjust outta betathrash and burnthe long view on short-term profiteerscontributors"}