{"URL": "https://www.wired.com/1999/02/turks-in-iraq", "heading": "turks in iraq", "subheading": "ignoring objections from baghdad, 10,000 turkish troops crossed into iraq friday to attack kurdish rebel bases. iraq denounced the incursion and demanded that the troops withdraw. while the army pressed its attack, protesters in southern turkey, angered by the arrest of kurdish leader abdullah ocalan earlier this week, fired on police. around 37,000 people have been killed since 1984, when fighting erupted over kurdish attempts to establish a separate homeland in southeastern turkey.", "author": "wired staff", "category": "culture", "type": "article", "timestamp": "02.19.1999 12:00 PM", "text": "ignoring objections from baghdad, 10,000 turkish troops crossed into iraq friday to attack kurdish rebel bases. iraq denounced the incursion and demanded that the troops withdraw. while the army pressed its attack, protesters in southern turkey, angered by the arrest of kurdish leader abdullah ocalan earlier this week, fired on police. around 37,000 people have been killed since 1984, when fighting erupted over kurdish attempts to establish a separate homeland in southeastern turkey. "}