{"URL": "https://www.wired.com/1999/07/passage-george-e-brown-jr-79", "heading": "passage: george e. brown jr., 79", "subheading": "the oldest member of the house of representatives and the ranking democrat on the house science committee represented california's 42nd district (san bernardino and environs) since 1962. brown, who was in his 18th term, was a strong booster of nasa and an advocate of space exploration. he underwent a heart-valve replacement in may but developed a post-operative infection, which proved fatal.", "author": "wired staff", "category": "culture", "type": "article", "timestamp": "07.16.1999 12:00 PM", "text": "the oldest member of the house of representatives and the ranking democrat on the house science committee represented california's 42nd district (san bernardino and environs) since 1962. brown, who was in his 18th term, was a strong booster of nasa and an advocate of space exploration. he underwent a heart-valve replacement in may but developed a post-operative infection, which proved fatal. "}